jthreads/___init__.py
jthreads/___init__.pyi
jthreads/countdownTimer.py
jthreads/countdownTimer.pyi
jthreads/loopingThread.py
jthreads/loopingThread.pyi
jthreads/py.typed
jthreads/timer.py
jthreads/timer.pyi
jthreads-1.0.1.dist-info/LICENSE
jthreads-1.0.1.dist-info/METADATA
jthreads-1.0.1.dist-info/WHEEL
jthreads-1.0.1.dist-info/top_level.txt
jthreads-1.0.1.dist-info/RECORD
